{
  "schemaVersion": "2026.01.results-v1",
  "effectId": "01KM1EMXR77MZJTM4T945MJSM6",
  "taskId": "quality-scorer",
  "invocationKey": "packman-multi-lang-edu:S000045:quality-scorer",
  "status": "ok",
  "result": {
    "criticalIssues": [],
    "overallScore": 95,
    "recommendations": [
      "Consider using std::unique_ptr for SDL resources (RAII pattern) in game_panel for more modern C++ style"
    ],
    "scores": {
      "annotations": 95,
      "behaviorMatch": 95,
      "buildTests": 100,
      "namingConventions": 90,
      "separationOfConcerns": 100
    }
  },
  "startedAt": "2026-03-18T21:47:02.296Z",
  "finishedAt": "2026-03-18T21:47:02.296Z",
  "value": {
    "criticalIssues": [],
    "overallScore": 95,
    "recommendations": [
      "Consider using std::unique_ptr for SDL resources (RAII pattern) in game_panel for more modern C++ style"
    ],
    "scores": {
      "annotations": 95,
      "behaviorMatch": 95,
      "buildTests": 100,
      "namingConventions": 90,
      "separationOfConcerns": 100
    }
  }
}
